server/__init__.py
server/server_start.py
server/common/__init__.py
server/common/decos.py
server/common/descrptrs.py
server/common/errors.py
server/common/metaclasses.py
server/common/utils.py
server/common/variables.py
server/logs/__init__.py
server/logs/config_client_log.py
server/logs/config_server_log.py
server/server/__init__.py
server/server/add_user.py
server/server/core.py
server/server/remove_user.py
server/server/server_database.py
server/server/server_gui.py
server/unit_tests/__init__.py
server/unit_tests/test_server.py
server/unit_tests/test_utils.py
yu_messenger_server-0.0.3.data/scripts/server_run
yu_messenger_server-0.0.3.dist-info/METADATA
yu_messenger_server-0.0.3.dist-info/WHEEL
yu_messenger_server-0.0.3.dist-info/top_level.txt
yu_messenger_server-0.0.3.dist-info/RECORD
