Metadata-Version: 2.1
Name: yu-messenger-server
Version: 0.0.3
Summary: Mess Server
Home-page: UNKNOWN
Author: Yuriy Verchenko
Author-email: yuverch@yandex.ru
License: UNKNOWN
Platform: UNKNOWN
Requires-Dist: PyQt5
Requires-Dist: sqlalchemy
Requires-Dist: pycryptodome
Requires-Dist: pycryptodomex
